[
	{
		"name": "河北交警总队",
		"child": [
			{
				"name": "保定交警支队",
				"child": [
					{
						"name": "交警大队一",
						"child": []
					},
					{
						"name": "交警大队二",
						"child": [
							{
								"name": "支队一",
								"child": []
							},
							{
								"name": "支队二",
								"child": []
							}
						]
					}
				]
			},
			{
				"name": "石家庄交警支队",
				"child": [
					{
						"name": "交警大队一",
						"child": [
							{
								"name": "支队一",
								"child": [
									{
										"name": "5级",
										"child":[]
									}
								]
							},
							{
								"name": "支队二",
								"child": []
							}
						]
					},
					{
						"name": "交警大队一",
						"child": []
					}
				]
			}
		]
	},
	{
		"name": "北京交警总队",
		"child": [
			{
				"name": "朝阳区交警支队",
				"child": [
					{
						"name": "交警大队一",
						"child": []
					},
					{
						"name": "交警大队二",
						"child": []
					}
				]
			},
			{
				"name": "海淀区交警支队",
				"child": [
					{
						"name": "交警大队一",
						"child": [
							{
								"name": "支队一",
								"child": [
									{
										"name": "5级",
										"child":[]
									}
								]
							},
							{
								"name": "支队二",
								"child": []
							}
						]
					},
					{
						"name": "交警大队一",
						"child": [
							{
								"name": "支队一",
								"child": [
									{
										"name": "5级",
										"child":[]
									}
								]
							},
							{
								"name": "支队一",
								"child": [
									{
										"name": "5级",
										"child":[]
									}
								]
							}
						]
					}
				]
			}
		]
	},
	{
		"name": "山东交警总队",
		"child":[]
	},
	{
		"name": "深圳交警总队",
		"child":[
			{
				"name": "交警大队一",
				"child": []
			}
		]
	},
	{
		"name": "山东交警总队",
		"child":[]
	}
]
